{
    "docslab":
    {
        "metadata": false,
        "archive": null,
        "include": ["submissions"],
        "download_artwork": false,
        "download_stories": false,
        "filename_format": "{id}_{title}",
        "sleep": 1.5,
        "sleep-request": 1.5
    },
    "kemonocafe":
    {
        "metadata": false,
        "archive": null,
        "filename_format": "{id}",
        "sleep": 1.5,
        "sleep-request": 1.5
    },
    "overflowingbra":
    {
        "metadata": false,
        "archive": null,
        "filename_format": "{title}",
        "sleep": 1.5,
        "sleep-request": 3
    },
    "tgcomics":
    {
        "metadata": false,
        "archive": null,
        "username": null,
        "password": null,
        "filename_format": "{title}",
        "sleep": 1.5,
        "sleep-request": 1.5
    },
    "transfur":
    {
        "metadata": false,
        "archive": null,
        "username": null,
        "password": null,
        "include": ["gallery", "sketches"],
        "filename_format": "{id}_{title}",
        "sleep": 1.5,
        "sleep-request": 1.5
    },
    "webtoon":
    {
        "metadata": false,
        "archive": null,
        "filename_format": "{id}_{title}",
        "sleep": 1.5,
        "sleep-request": 1.5,
        "stitch_images": true,
        "only_stitched": false
    }
}
